{"":[["%w%%c%","%w%%c%","%w%%c%"],["%w%%c%","%w%%c%","%w%%c%"],[null,"%i%stick",null]],"bo":[["%d%%c%","%d%%c%","%d%%c%"],["%d%%c%","%b%","%d%%c%"],["%d%%c%","%d%%c%","%d%%c%"]],"bri":[[null,"%d%%c%",null],[null,"%i%brick",null],[null,"%b%",null]],"mc":[null,[null,"%d%%c%",null],[null,"%b%",null]],"cre":[[null,"%d%%c%",null],[null,"%i%creeper",null],[null,"%b%",null]],"cr":[["%d%%c%",null,"%d%%c%"],[null,"%d%%c%",null],["%d%%c%","%b%","%d%%c%"]],"cbo":[[null,"%d%%c%",null],[null,"%i%vine",null],[null,"%b%",null]],"ld":[["%d%%c%","%d%%c%",null],["%d%%c%","%b%",null],null],"rd":[[null,"%d%%c%","%d%%c%"],[null,"%b%","%d%%c%"],null],"rud":[null,[null,"%b%","%d%%c%"],[null,"%d%%c%","%d%%c%"]],"lud":[null,["%d%%c%","%b%",null],["%d%%c%","%d%%c%",null]],"flo":[[null,"%d%%c%",null],[null,"%i%flower_oxeye_daisy",null],[null,"%b%",null]],"gra":[["%d%%c%","%b%","%d%%c%"],[null,"%d%%c%",null],[null,"%d%%c%",null]],"hh":[["%d%%c%","%d%%c%","%d%%c%"],["%d%%c%","%d%%c%","%d%%c%"],[null,"%b%",null]],"hhb":[[null,"%b%",null],["%d%%c%","%d%%c%","%d%%c%"],["%d%%c%","%d%%c%","%d%%c%"]],"vh":[["%d%%c%","%d%%c%",null],["%d%%c%","%d%%c%","%b%"],["%d%%c%","%d%%c%",null]],"vhr":[[null,"%d%%c%","%d%%c%"],["%b%","%d%%c%","%d%%c%"],[null,"%d%%c%","%d%%c%"]],"moj":[[null,"%d%%c%",null],[null,"%i%apple_golden",null],[null,"%b%",null]],"mr":[[null,"%d%%c%",null],["%d%%c%","%b%","%d%%c%"],[null,"%d%%c%",null]],"sku":[[null,"%d%%c%",null],[null,"%i%wither",null],[null,"%b%",null]],"ss":[["%d%%c%",null,"%d%%c%"],["%d%%c%","%b%","%d%%c%"],null],"bl":[null,[null,"%b%",null],["%d%%c%",null,null]],"br":[null,[null,"%b%",null],[null,null,"%d%%c%"]],"tl":[["%d%%c%",null,null],[null,"%b%",null],null],"tr":[[null,null,"%d%%c%"],[null,"%b%",null],null],"sc":[["%b%","%d%%c%",null],["%d%%c%","%d%%c%","%d%%c%"],[null,"%d%%c%",null]],"bs":[null,[null,"%b%",null],["%d%%c%","%d%%c%","%d%%c%"]],"cs":[[null,"%d%%c%",null],["%b%","%d%%c%",null],[null,"%d%%c%",null]],"dls":[["%b%",null,"%d%%c%"],[null,"%d%%c%",null],["%d%%c%",null,null]],"drs":[["%d%%c%",null,"%b%"],[null,"%d%%c%",null],[null,null,"%d%%c%"]],"ls":[["%d%%c%",null,null],["%d%%c%","%b%",null],["%d%%c%",null,null]],"ms":[[null,"%b%",null],["%d%%c%","%d%%c%","%d%%c%"],null],"rs":[[null,null,"%d%%c%"],[null,"%b%","%d%%c%"],[null,null,"%d%%c%"]],"ts":[["%d%%c%","%d%%c%","%d%%c%"],[null,"%b%",null],null],"bt":[null,[null,"%d%%c%",null],["%d%%c%","%b%","%d%%c%"]],"tt":[["%d%%c%","%b%","%d%%c%"],[null,"%d%%c%",null],null],"bts":[null,["%d%%c%","%b%","%d%%c%"],[null,"%d%%c%",null]],"tts":[[null,"%d%%c%",null],["%d%%c%","%b%","%d%%c%"],null]}